DPD/__init__.py
DPD/dpd.py
DPD/util.py
DPD-0.0.3.dist-info/LICENSE
DPD-0.0.3.dist-info/METADATA
DPD-0.0.3.dist-info/WHEEL
DPD-0.0.3.dist-info/top_level.txt
DPD-0.0.3.dist-info/RECORD
