Metadata-Version: 2.1
Name: DPD
Version: 0.0.3
Summary: Dendrogram Prototypical Discourse generator
Home-page: UNKNOWN
Author: Sergio Peignier
Author-email: sergio.peignier@insa-lyon.fr
License: UNKNOWN
Platform: UNKNOWN
Classifier: Programming Language :: Python :: 3
Classifier: License :: OSI Approved :: GNU General Public License (GPL)
Classifier: Operating System :: OS Independent
Requires-Dist: pandas
Requires-Dist: numpy
Requires-Dist: nltk
Requires-Dist: gensim
Requires-Dist: sklearn
Requires-Dist: scipy
Requires-Dist: matplotlib
